{
  "logConfig": {
    "enabled": true,
    "level": "info"
  },
  "httpConfig": {
    "host": "0.0.0.0",
    "port": 8080,
    "cors": {
      "enabled": true,
      "origins": [
        "*"
      ],
      "methods": [
        "HEAD",
        "GET",
        "POST",
        "PUT",
        "DELETE",
        "OPTIONS"
      ],
      "headers": [
        "Content-Type",
        "Authorization"
      ]
    },
    "clientCache": {
      "enabled": true,
      "maxAge": 3600
    },
    "httpsConfig": {
      "enabled": false,
      "cert": "",
      "key": ""
    }
  },
  "fileConfig": {
    "baseFileStoragePath": "data",
    "allowFolderCreation": true,
    "uploadPath": "upload",
    "uploadLimit": 1073741824,
    "uploadTimeout": 7200
  },
  "cacheConfig": {
    "cacheType": "MemoryCache",
    "MemoryCache": {
      "maxEntries": 1000,
      "defaultTTL": 60
    }
  },
  "imageConfig": {
    "defaultFormat": "jpeg",
    "allowedFormats": [
      "png",
      "jpeg",
      "gif"
    ],
    "strictMode": true,
    "allowedSizes": [
      16,
      32,
      64,
      128,
      256,
      512,
      1024
    ],
    "maxFileSize": 20971520,
    "maxWidth": 4096,
    "maxHeight": 4096
  },
  "jwtConfig": {
    "enabled": true,
    "algorithm": "HS256",
    "Security": {
      "signingKey": "goflet",
      "publicKey": "",
      "privateKey": ""
    },
    "trustedIssuers": null
  },
  "cronConfig": {
    "deleteEmptyFolder": 3600,
    "cleanOutdatedFile": 3600
  }
}
